pykdebugparser/__init__.py
pykdebugparser/__main__.py
pykdebugparser/callstacks_parser.py
pykdebugparser/kd_buf_parser.py
pykdebugparser/kevent.py
pykdebugparser/os_log_event.py
pykdebugparser/pykdebugparser.py
pykdebugparser/trace.codes
pykdebugparser/trace_codes.py
pykdebugparser/traces_parser.py
pykdebugparser/trace_handlers/__init__.py
pykdebugparser/trace_handlers/bsd.py
pykdebugparser/trace_handlers/dyld.py
pykdebugparser/trace_handlers/fsystem.py
pykdebugparser/trace_handlers/mach.py
pykdebugparser/trace_handlers/perf.py
pykdebugparser/trace_handlers/trace.py
pykdebugparser/trace_handlers/turnstile.py
pykdebugparser-1.2.6.dist-info/licenses/LICENSE
tests/conftest.py
tests/test_kevent.py
tests/test_os_log_event.py
tests/test_pykdebugparser.py
tests/test_trace_codes.py
tests/callstacks/test_callstacks_parser.py
tests/traces/test_bsd.py
tests/traces/test_dyld.py
tests/traces/test_mach.py
tests/traces/test_perf.py
tests/traces/test_trace.py
tests/traces/test_turnstile.py
pykdebugparser-1.2.6.dist-info/METADATA
pykdebugparser-1.2.6.dist-info/WHEEL
pykdebugparser-1.2.6.dist-info/entry_points.txt
pykdebugparser-1.2.6.dist-info/top_level.txt
pykdebugparser-1.2.6.dist-info/RECORD
