Metadata-Version: 2.4
Name: pykdebugparser
Version: 1.2.6
Summary: Python parser for kdebug events
Author: Matan Perelman
Author-email: matan1008@gmail.com
License: MIT License
Project-URL: Homepage, https://github.com/matan1008/pykdebugparser
Project-URL: Source, https://github.com/matan1008/pykdebugparser
Classifier: Programming Language :: Python :: 3.8
Classifier: Programming Language :: Python :: 3.9
Classifier: Programming Language :: Python :: 3.10
Classifier: Programming Language :: Python :: 3.11
Classifier: Programming Language :: Python :: 3.12
Classifier: Programming Language :: Python :: 3.13
Requires-Python: >=3.8
License-File: LICENSE
Requires-Dist: construct
Requires-Dist: pygments
Requires-Dist: click
Requires-Dist: termcolor
Provides-Extra: testing
Requires-Dist: pytest; extra == "testing"
Dynamic: license-file
